paz/__init__.py
paz/applications.py
paz/abstract/__init__.py
paz/abstract/loader.py
paz/abstract/messages.py
paz/abstract/processor.py
paz/abstract/sequence.py
paz/backend/__init__.py
paz/backend/anchors.py
paz/backend/angles.py
paz/backend/boxes.py
paz/backend/camera.py
paz/backend/heatmaps.py
paz/backend/keypoints.py
paz/backend/munkres.py
paz/backend/render.py
paz/backend/standard.py
paz/backend/groups/SE3.py
paz/backend/groups/SO3.py
paz/backend/groups/__init__.py
paz/backend/groups/quaternion.py
paz/backend/image/__init__.py
paz/backend/image/draw.py
paz/backend/image/image.py
paz/backend/image/opencv_image.py
paz/backend/image/tensorflow_image.py
paz/datasets/CMU_poanoptic.py
paz/datasets/__init__.py
paz/datasets/cityscapes.py
paz/datasets/coco.py
paz/datasets/fat.py
paz/datasets/fer.py
paz/datasets/ferplus.py
paz/datasets/human36m.py
paz/datasets/omniglot.py
paz/datasets/open_images.py
paz/datasets/shapes.py
paz/datasets/utils.py
paz/datasets/voc.py
paz/evaluation/__init__.py
paz/evaluation/detection.py
paz/models/__init__.py
paz/models/layers.py
paz/models/classification/__init__.py
paz/models/classification/protonet.py
paz/models/classification/xception.py
paz/models/detection/__init__.py
paz/models/detection/haar_cascade.py
paz/models/detection/ssd300.py
paz/models/detection/ssd512.py
paz/models/detection/utils.py
paz/models/detection/efficientdet/__init__.py
paz/models/detection/efficientdet/efficientdet.py
paz/models/detection/efficientdet/efficientdet_blocks.py
paz/models/detection/efficientdet/efficientnet.py
paz/models/detection/efficientdet/layers.py
paz/models/keypoint/__init__.py
paz/models/keypoint/detnet.py
paz/models/keypoint/hrnet.py
paz/models/keypoint/iknet.py
paz/models/keypoint/keypointnet.py
paz/models/keypoint/projector.py
paz/models/keypoint/simplebaselines.py
paz/models/pose_estimation/__init__.py
paz/models/pose_estimation/higher_hrnet.py
paz/models/segmentation/__init__.py
paz/models/segmentation/unet.py
paz/optimization/__init__.py
pypaz-0.2.5.dist-info/LICENSE
pypaz-0.2.5.dist-info/METADATA
pypaz-0.2.5.dist-info/WHEEL
pypaz-0.2.5.dist-info/top_level.txt
pypaz-0.2.5.dist-info/RECORD
